{
    "label": "🚲",
    "title": "Who is allowed to park a bicycle here?",
    "geometry": {
        "area": true,
        "point": true,
        "vertex": false,
        "line": true
    },
    "filters": [
        {
            "tagValue": "bicycle_parking",
            "relation": "=",
            "tagKey": "amenity",
            "included": "include"
        },
        {
            "included": "include",
            "tagKey": "access",
            "relation": "=",
            "tagValue": ""
        }
    ],
    "tagKeys": [
        "access"
    ]
}